MANIFEST.in
README.rst
setup.py
void_reconstructor/__init__.py
void_reconstructor/reconstruction.py
void_reconstructor/volume_division.py
void_reconstructor.egg-info/PKG-INFO
void_reconstructor.egg-info/SOURCES.txt
void_reconstructor.egg-info/dependency_links.txt
void_reconstructor.egg-info/requires.txt
void_reconstructor.egg-info/top_level.txt