Metadata-Version: 1.2
Name: void-reconstructor
Version: 1.2.0
Summary: Tools for reconstructing the velocities in a LCDM universe using the Jonker-Volgenant algorithm
Home-page: UNKNOWN
Author-email: tobias.meier@epfl.ch
License: UNKNOWN
Platform: UNKNOWN
Requires-Python: >=3
